examples
tnet
