Metadata-Version: 1.0
Name: tnet
Version: 0.0.1a1
Summary: Torch and torchnet like library for building and training neural networks in Theano
Home-page: https://github.com/mhjabreel/tnet
Author: Mohammed Jabreel
Author-email: mhjabreel@gmail.com
License: Apache 2.0
Platform: UNKNOWN
